MANIFEST.in
README.txt
setup.cfg
setup.py
eoldas/Identity.py
eoldas/__init__.py
eoldas/eoldas_ConfFile.py
eoldas/eoldas_DModel_Operator.py
eoldas/eoldas_Files.py
eoldas/eoldas_Kernel_Operator.py
eoldas/eoldas_Lib.py
eoldas/eoldas_Observation_Operator.py
eoldas/eoldas_Operator.py
eoldas/eoldas_ParamStorage.py
eoldas/eoldas_Parser.py
eoldas/eoldas_Solver.py
eoldas/eoldas_SpecialVariable.py
eoldas/eoldas_Spectral.py
eoldas/eoldas_State.py
eoldas/kernels.py
eoldas.egg-info/PKG-INFO
eoldas.egg-info/SOURCES.txt
eoldas.egg-info/dependency_links.txt
eoldas.egg-info/not-zip-safe
eoldas.egg-info/requires.txt
eoldas.egg-info/top_level.txt
eoldas/config_files/default.conf
eoldas/config_files/eoldas_config.conf
scripts/eoldas_run.py