Metadata-Version: 1.0
Name: eoldas
Version: 1.0.8dev
Summary: An Earth Observation Land Data Assimilation System (EO-LDAS)
Home-page: http://www.assimila.eu/eoldas
Author: Jose Gomez-Dans/NCEO & University College London
Author-email: j.gomez-dans@ucl.ac.uk
License: UNKNOWN
Download-URL: https://github.com/jgomezdans/eoldas/zipball/master
Platform: UNKNOWN
Classifier: Intended Audience :: Science/Research
Classifier: Intended Audience :: Developers
Classifier: License :: OSI Approved
Classifier: Programming Language :: Fortran
Classifier: Programming Language :: Python
Classifier: Topic :: Software Development
Classifier: Topic :: Scientific/Engineering
Classifier: Operating System :: Microsoft :: Windows
Classifier: Operating System :: POSIX
Classifier: Operating System :: Unix
Classifier: Operating System :: MacOS
